
{
    "Code" : "Portrait.Illust.Basic19",
    "SplitSpecType" : "Single",
    "TextureBuildPreset" : "NguiAtlas_HighHighMid",
    "Atlas"              : 
    {
        "Prefix" : "Portrait/Illust/",
        "ReferenceSpriteList" : null,
        "SplitLanguage"       : false,
        "AtlasList"           : 
        [
            {
                "Language" : "Unknown",
                "AtlasLink" : 
                {
                    "GUID" : "8abb42f5a028c3347bd433c64427777a",
                    "OrigAssetPath" : "Assets/Resources.Export/NguiAtlas/ResourceData/Portrait/HeroIllust/Basic/BasicIllust19.prefab",
                    "IsSubAsset"    : false
                }
            }
        ]
    }
}