
{
    "Code" : "Loading.Hero.Taily",
    "SplitSpecType" : "Single",
    "TextureBuildPreset" : "Single",
    "Atlas"              : 
    {
        "Prefix" : "Portrait/HeroFull_BG/",
        "ReferenceSpriteList" : null,
        "SplitLanguage"       : false,
        "AtlasList"           : 
        [
            {
                "Language" : "Unknown",
                "AtlasLink" : 
                {
                    "GUID" : "9e97816b5ee8cc64daceeae3006dfe8a",
                    "OrigAssetPath" : "Assets/Resources.Export/NguiAtlas/ResourceData/Portrait/HeroFull_BG/Atlas_Taily.prefab",
                    "IsSubAsset"    : false
                }
            }
        ]
    }
}