
{
    "Code" : "UI.Portrait.HeroAchievement5",
    "SplitSpecType" : "SplitHighHighMid",
    "TextureBuildPreset" : "SplitHighHighMid",
    "Atlas"              : 
    {
        "Prefix" : "Portrait/HeroFull/",
        "ReferenceSpriteList" : null,
        "SplitLanguage"       : false,
        "AtlasList"           : 
        [
            {
                "Language" : "Unknown",
                "AtlasLink" : 
                {
                    "GUID" : "b6e55e61ecd64594695dc7269d49357e",
                    "OrigAssetPath" : "Assets/Resources.Export/NguiAtlas/ResourceData/Portrait/HeroFull/HeroAchievement5Atlas.prefab",
                    "IsSubAsset"    : false
                }
            }
        ]
    }
}